{
  "_fv": 18,
  "_type": "tool",
  "definition": {
    "renderType": 0,
    "texture": "ardenium_axe_texture",
    "customModelName": "Normal",
    "name": "Ardenium Axe",
    "specialInfo": [],
    "creativeTab": {
      "value": "TOOLS"
    },
    "toolType": "Axe",
    "harvestLevel": 30,
    "efficiency": 15.0,
    "attackSpeed": 1.0,
    "enchantability": 10,
    "damageVsEntity": 4.0,
    "usageCount": 300,
    "blocksAffected": [],
    "hasGlow": false,
    "repairItems": [],
    "immuneToFire": true,
    "stayInGridWhenCrafting": false,
    "damageOnCrafting": false
  }
}