{"stats":{"minecraft:custom":{"minecraft:time_since_rest":2626,"minecraft:sprint_one_cm":1420,"minecraft:damage_taken":320,"minecraft:walk_one_cm":26641,"minecraft:mob_kills":4,"minecraft:drop":8,"minecraft:damage_dealt":1340,"minecraft:fly_one_cm":11173,"minecraft:crouch_one_cm":61,"minecraft:play_one_minute":23678,"minecraft:deaths":1,"minecraft:sneak_time":135,"minecraft:walk_under_water_one_cm":7455,"minecraft:jump":176,"minecraft:leave_game":1,"minecraft:time_since_death":2487,"minecraft:walk_on_water_one_cm":3386,"minecraft:fall_one_cm":5051},"minecraft:dropped":{"lucky_block:ghastshovel":1,"minecraft:barrier":1,"minecraft:birch_log":6},"minecraft:crafted":{"minecraft:birch_planks":24},"minecraft:picked_up":{"minecraft:birch_log":13,"lucky_block:ghast_sword":1,"minecraft:barrier":1,"minecraft:feather":1,"minecraft:chicken":1,"minecraft:sand":32,"minecraft:oak_log":2,"minecraft:diorite":3,"minecraft:dirt":142,"minecraft:wheat_seeds":1,"minecraft:iron_ingot":4,"minecraft:beef":2,"minecraft:granite":2,"minecraft:iron_ore":3,"lucky_block:ghastshovel":1,"minecraft:poppy":1,"minecraft:cobblestone":38},"minecraft:killed":{"minecraft:zombie":1,"minecraft:chicken":1,"minecraft:iron_golem":1,"minecraft:cow":1},"minecraft:mined":{"minecraft:birch_log":7,"minecraft:iron_ore":3,"minecraft:grass_path":1,"minecraft:granite":5,"minecraft:grass":4,"minecraft:grass_block":37,"minecraft:oak_log":5,"minecraft:sand":40,"minecraft:dirt":181,"minecraft:stone":72,"minecraft:diorite":3,"minecraft:oak_leaves":1},"minecraft:used":{"minecraft:barrier":75,"minecraft:poppy":1,"lucky_block:ghastshovel":378,"minecraft:dirt":39,"minecraft:cobblestone":10,"minecraft:beef":2,"lucky_block:ghast_sword":18,"lucky_block:ghasthoe":8,"lucky_block:ghastpickaxe":86}},"DataVersion":2586}